raygun4py/__init__.py
raygun4py/cli.py
raygun4py/http_utilities.py
raygun4py/raygunmsgs.py
raygun4py/raygunprovider.py
raygun4py/utilities.py
raygun4py/middleware/__init__.py
raygun4py/middleware/django.py
raygun4py/middleware/flask.py
raygun4py/middleware/wsgi.py
raygun4py-4.1.0.dist-info/LICENSE
raygun4py-4.1.0.dist-info/METADATA
raygun4py-4.1.0.dist-info/WHEEL
raygun4py-4.1.0.dist-info/entry_points.txt
raygun4py-4.1.0.dist-info/top_level.txt
raygun4py-4.1.0.dist-info/RECORD
