Metadata-Version: 2.1
Name: raygun4py
Version: 4.1.0
Summary: Official Raygun provider for Python 2.7 and Python 3+
Home-page: https://raygun.com
Author: Raygun
Author-email: hello@raygun.io
License: LICENSE
Platform: UNKNOWN
Classifier: Development Status :: 5 - Production/Stable
Classifier: Intended Audience :: Developers
Classifier: License :: OSI Approved :: MIT License
Classifier: Programming Language :: Python
Classifier: Programming Language :: Python :: 2.7
Classifier: Programming Language :: Python :: 3
Classifier: Programming Language :: Python :: 3.1
Classifier: Programming Language :: Python :: 3.2
Classifier: Programming Language :: Python :: 3.3
Classifier: Programming Language :: Python :: 3.4
Classifier: Programming Language :: Python :: 3.5
Classifier: Programming Language :: Python :: 3.6
Classifier: Programming Language :: Python :: 3.7
Classifier: Topic :: Communications
Requires-Dist: jsonpickle (>=0.9.2)
Requires-Dist: blinker (>=1.3.0)
Requires-Dist: requests (>=2.9.1)
